deepassimilate/__init__.py
deepassimilate/core.py
deepassimilate/dataset.py
deepassimilate/deepassimilate.py
deepassimilate/loss.py
deepassimilate/models.py
deepassimilate/train.py
deepassimilate/utils.py
DeepAssimilate-0.1.0.dist-info/LICENSE
DeepAssimilate-0.1.0.dist-info/METADATA
DeepAssimilate-0.1.0.dist-info/WHEEL
DeepAssimilate-0.1.0.dist-info/top_level.txt
DeepAssimilate-0.1.0.dist-info/RECORD
