Metadata-Version: 2.1
Name: DeepAssimilate
Version: 0.1.0
Summary: Description of DeepAssimilate package
Home-page: https://github.com/your-username/DeepAssimilate
Author: Your Name
Author-email: your.email@example.com
Classifier: Programming Language :: Python :: 3
Classifier: License :: OSI Approved :: MIT License
Classifier: Operating System :: OS Independent
Requires-Python: >=3.6
License-File: LICENSE
Requires-Dist: torch>=1.7.1
Requires-Dist: numpy
Requires-Dist: opencv-python
Requires-Dist: scikit-learn
Requires-Dist: pytest
Requires-Dist: torchvision
Requires-Dist: tensorboard
Requires-Dist: diffusers
Requires-Dist: matplotlib
